frontend/build/.DS_Store
frontend/build/asset-manifest.json
frontend/build/index.html
frontend/build/precache-manifest.c6f509cc82dea392264da20287ae09f1.js
frontend/build/service-worker.js
frontend/build/static/css/2.f6cb0e92.chunk.css
frontend/build/static/css/2.f6cb0e92.chunk.css.map
frontend/build/static/js/2.84b35cd3.chunk.js
frontend/build/static/js/2.84b35cd3.chunk.js.LICENSE.txt
frontend/build/static/js/2.84b35cd3.chunk.js.map
frontend/build/static/js/main.993e9c2b.chunk.js
frontend/build/static/js/main.993e9c2b.chunk.js.map
frontend/build/static/js/runtime-main.c8a21426.js
frontend/build/static/js/runtime-main.c8a21426.js.map
labelling/__init__.py
labelling/__main__.py
labelling/notebook/__init__.py
labelling/notebook/api_files.py
labelling_notebook-0.3.2.dist-info/entry_points.txt
labelling_notebook-0.3.2.dist-info/LICENSE
labelling_notebook-0.3.2.dist-info/WHEEL
labelling_notebook-0.3.2.dist-info/METADATA
labelling_notebook-0.3.2.dist-info/RECORD
